{
  "京城大师赛": [
    {
      "来源": "https://space.bilibili.com/19106800/lists/6648988?type=season",
      "mid": 19106800,
      "合集ID": 6648988,
      "合集标题": "紫禁之巅",
      "视频": [
        {
          "标题": "20251028 季前赛 Day-1 第一局-预女猎白混",
          "链接": "https://www.bilibili.com/video/BV1MHykB5EHo"
        },
        {
          "标题": "20251028 季前赛 Day-1 第二局-盗宝大师",
          "链接": "https://www.bilibili.com/video/BV1MHykB5E4x"
        },
        {
          "标题": "20251028 季前赛 Day-1 第三局-机械狼通灵师",
          "链接": "https://www.bilibili.com/video/BV1UHykB5EJ2"
        },
        {
          "标题": "20251029 季前赛 Day-2 第一局-预女猎白混",
          "链接": "https://www.bilibili.com/video/BV1zNyWBVEjA"
        },
        {
          "标题": "20251029 季前赛 Day-2 第二局-孤注一掷",
          "链接": "https://www.bilibili.com/video/BV17uyWB6EkP"
        },
        {
          "标题": "20251029 季前赛 Day-2 机械狼通灵师",
          "链接": "https://www.bilibili.com/video/BV1ouyWBzE2G"
        },
        {
          "标题": "20251030 季前赛 Day-4 第一局-预女猎白混",
          "链接": "https://www.bilibili.com/video/BV1vayeBvEo9"
        },
        {
          "标题": "20251030 季前赛 Day-4 第二局-假面舞会",
          "链接": "https://www.bilibili.com/video/BV15vyeBYEBL"
        },
        {
          "标题": "20251030 季前赛 Day-4 第三局-机械狼通灵师",
          "链接": "https://www.bilibili.com/video/BV1ReyeBAExm"
        },
        {
          "标题": "20251031 季前赛 Day-4 第一局-预女猎白混",
          "链接": "https://www.bilibili.com/video/BV1ED1uBuEku"
        },
        {
          "标题": "20251031 季前赛 Day-4 第二局-机械狼通灵师",
          "链接": "https://www.bilibili.com/video/BV1ED1uBuEkK"
        },
        {
          "标题": "20251031 季前赛 Day-4 第三局-捣蛋鬼",
          "链接": "https://www.bilibili.com/video/BV1ED1uBuEkG"
        },
        {
          "标题": "20251104 表演赛 Day-1 第一局-预女猎白混",
          "链接": "https://www.bilibili.com/video/BV1HF1EBNEwJ"
        },
        {
          "标题": "20251104 表演赛 Day-1 第二局-假面舞会",
          "链接": "https://www.bilibili.com/video/BV1HF1EBNEGu"
        },
        {
          "标题": "20251104 表演赛 Day-1 第三局-机械狼通灵师",
          "链接": "https://www.bilibili.com/video/BV1wF1EBKEa9"
        },
        {
          "标题": "20251105 表演赛 Day-2 第一局-预女猎白混",
          "链接": "https://www.bilibili.com/video/BV1Wg14B8E4m"
        },
        {
          "标题": "20251105 表演赛 Day-2 第二局-盗宝大师",
          "链接": "https://www.bilibili.com/video/BV1Wg14B8EhZ"
        },
        {
          "标题": "20251105 表演赛 Day-2 第三局-机械狼通灵师",
          "链接": "https://www.bilibili.com/video/BV1Wg14B8E7k"
        },
        {
          "标题": "20251106 表演赛 Day-3 第一局-针锋相杠",
          "链接": "https://www.bilibili.com/video/BV1vo2PBXENg"
        },
        {
          "标题": "20251106 表演赛 Day-3 第二局-假面舞会",
          "链接": "https://www.bilibili.com/video/BV1eo2PBXEDm"
        },
        {
          "标题": "20251106 表演赛 Day-3 第三局-机械狼通灵师",
          "链接": "https://www.bilibili.com/video/BV1eo2PBXErD"
        },
        {
          "标题": "20251107 表演赛 Day-4 第一局-预女猎禁混",
          "链接": "https://www.bilibili.com/video/BV1ep11BPEZW"
        },
        {
          "标题": "20251107 表演赛 Day-4 第二局-盗宝大师",
          "链接": "https://www.bilibili.com/video/BV1be11BdEGE"
        },
        {
          "标题": "20251107 表演赛 Day-4 第三局-机械狼通灵师",
          "链接": "https://www.bilibili.com/video/BV1ue11BoEtm"
        },
        {
          "标题": "20251111 正赛 第一期 Day-1 第一局-预女猎白混",
          "链接": "https://www.bilibili.com/video/BV17bkyB8Emd"
        },
        {
          "标题": "20251111 正赛 第一期 Day-1 第二局-假面舞会",
          "链接": "https://www.bilibili.com/video/BV1fbkyB8EuX"
        },
        {
          "标题": "20251111 正赛 第一期 Day-1 第三局-机械狼通灵师",
          "链接": "https://www.bilibili.com/video/BV1qakyBtEPk"
        },
        {
          "标题": "20251111 正赛 第一期 Day-1 第四局-机械狼通灵师",
          "链接": "https://www.bilibili.com/video/BV1nskyBAEEa"
        },
        {
          "标题": "20251112 正赛 第一期 Day-2 第一局-预女猎白混",
          "链接": "https://www.bilibili.com/video/BV1TQCEBkE2u"
        },
        {
          "标题": "20251112 正赛 第一期 Day-2 第二局-盗宝大师",
          "链接": "https://www.bilibili.com/video/BV13yCEB7EQY"
        },
        {
          "标题": "20251112 正赛 第一期 Day-2 第三局-机械狼通灵师",
          "链接": "https://www.bilibili.com/video/BV1GkCEBUEcM"
        },
        {
          "标题": "20251113 正赛 第一期 Day-3 第一局-预女猎白混",
          "链接": "https://www.bilibili.com/video/BV14yCABwEzD"
        },
        {
          "标题": "20251113 正赛 第一期 Day-3 第二局-盗宝大师",
          "链接": "https://www.bilibili.com/video/BV1tyCABwETu"
        },
        {
          "标题": "20251113 正赛 第一期 Day-3 第三局-机械狼通灵师",
          "链接": "https://www.bilibili.com/video/BV1tyCABwEs1"
        },
        {
          "标题": "20251114 正赛 第一期 Day-4 第一局-预女猎白混",
          "链接": "https://www.bilibili.com/video/BV12JC3BnE5G"
        },
        {
          "标题": "20251114 正赛 第一期 Day-4 第二局-魔幻对决",
          "链接": "https://www.bilibili.com/video/BV12JC3BnEDx"
        },
        {
          "标题": "20251114 正赛 第一期 Day-4 第三局-机械狼通灵师",
          "链接": "https://www.bilibili.com/video/BV12JC3BnEpR"
        },
        {
          "标题": "20251118 正赛 第二期 Day-1 第一局-针锋相杠",
          "链接": "https://www.bilibili.com/video/BV1h1yVBNEHT"
        },
        {
          "标题": "20251118 正赛 第二期 Day-1 第二局-魔幻对局",
          "链接": "https://www.bilibili.com/video/BV181yVBNEy9"
        },
        {
          "标题": "20251118 正赛 第二期 Day-1 第三局-机械狼通灵师",
          "链接": "https://www.bilibili.com/video/BV181yVBNEyr"
        },
        {
          "标题": "20251119 正赛 第二期 Day-2 第一局-预女猎白混",
          "链接": "https://www.bilibili.com/video/BV1msyHBDESb"
        },
        {
          "标题": "20251119 正赛 第二期 Day-2 第二局-假面舞会",
          "链接": "https://www.bilibili.com/video/BV1UWyHBHEPV"
        },
        {
          "标题": "20251119 正赛 第二期 Day-2 第三局-机械狼通灵师",
          "链接": "https://www.bilibili.com/video/BV1QLyHBoEom"
        },
        {
          "标题": "20251120 正赛 第二期 Day-3 第一局-预女猎白混",
          "链接": "https://www.bilibili.com/video/BV1sByABFE7g"
        },
        {
          "标题": "20251120 正赛 第二期 Day-3 第二局-假面舞会",
          "链接": "https://www.bilibili.com/video/BV1bbyABKEiC"
        },
        {
          "标题": "20251120 正赛 第二期 Day-3 第三局-机械狼通灵师",
          "链接": "https://www.bilibili.com/video/BV1D4yABqEwj"
        },
        {
          "标题": "20251121 正赛 第二期 Day-4 第一局-预女猎白混",
          "链接": "https://www.bilibili.com/video/BV1PfU7B2EQB"
        },
        {
          "标题": "20251121 正赛 第二期 Day-4 第二局-假面舞会",
          "链接": "https://www.bilibili.com/video/BV1NZU7B7Ewx"
        },
        {
          "标题": "20251121 正赛 第二期 Day-4 第三局-机械狼通灵师",
          "链接": "https://www.bilibili.com/video/BV1AwUEByEAu"
        },
        {
          "标题": "20251125 正赛 第三期 Day-1 第一局-预女猎白混",
          "链接": "https://www.bilibili.com/video/BV1MeUXBDETr"
        },
        {
          "标题": "20251125 正赛 第三期 Day-1 第二局-盗宝大师",
          "链接": "https://www.bilibili.com/video/BV1meUXBSEBe"
        },
        {
          "标题": "20251125 正赛 第三期 Day-1 第三局-机械狼通灵师",
          "链接": "https://www.bilibili.com/video/BV1UeUXBSEcv"
        },
        {
          "标题": "20251126 正赛 第三期 Day-2 第一局-预女猎白混",
          "链接": "https://www.bilibili.com/video/BV1V3UvBkE3g"
        },
        {
          "标题": "20251126 正赛 第三期 Day-2 第二局-假面舞会",
          "链接": "https://www.bilibili.com/video/BV1G3UvBkEoD"
        },
        {
          "标题": "20251126 正赛 第三期 Day-2 第三局-机械狼通灵师",
          "链接": "https://www.bilibili.com/video/BV1e3UvBkEAw"
        },
        {
          "标题": "20251127 特辑 京师和TA的朋友们 第一局-预女猎白",
          "链接": "https://www.bilibili.com/video/BV1JAS3B9EJY"
        },
        {
          "标题": "20251127 特辑 京师和TA的朋友们 第二局-禁言长老",
          "链接": "https://www.bilibili.com/video/BV1zAS3B9EXQ"
        },
        {
          "标题": "20251127 特辑 京师和TA的朋友们 第三局-黑狼王骑士",
          "链接": "https://www.bilibili.com/video/BV1JAS3B9Ebx"
        },
        {
          "标题": "20251128 正赛 第三期 Day-4 第一局-预女猎白混",
          "链接": "https://www.bilibili.com/video/BV166SnBJEa4"
        },
        {
          "标题": "20251128 正赛 第三期 Day-4 第二局-盗宝大师",
          "链接": "https://www.bilibili.com/video/BV1c6SnBnEwE"
        },
        {
          "标题": "20251128 正赛 第三期 Day-4 第三局-机械狼通灵师",
          "链接": "https://www.bilibili.com/video/BV1F6SnBnEX4"
        },
        {
          "标题": "20251202 正赛 第四期 Day-1 第一局-预女猎白混",
          "链接": "https://www.bilibili.com/video/BV1SqSbBWEA5"
        },
        {
          "标题": "20251202 正赛 第四期 Day-1 第二局-假面舞会",
          "链接": "https://www.bilibili.com/video/BV1bqSbBsEQN"
        },
        {
          "标题": "20251202 正赛 第四期 Day-1 第三局-机械狼通灵师",
          "链接": "https://www.bilibili.com/video/BV1SqSbBWE8B"
        },
        {
          "标题": "20251203 正赛 第四期 Day-2 第一局-预女猎白混",
          "链接": "https://www.bilibili.com/video/BV1c42tBaEbY"
        },
        {
          "标题": "20251203 正赛 第四期 Day-2 第二局-盗宝大师",
          "链接": "https://www.bilibili.com/video/BV1642tBhE2g"
        },
        {
          "标题": "20251203 正赛 第四期 Day-2 第三局-机械狼通灵师",
          "链接": "https://www.bilibili.com/video/BV1r42tBhEEu"
        },
        {
          "标题": "20251204 正赛 第四期 Day-3 第一局-预女猎白混",
          "链接": "https://www.bilibili.com/video/BV1Te2BBqE5K"
        },
        {
          "标题": "20251204 正赛 第四期 Day-3 第二局-假面舞会",
          "链接": "https://www.bilibili.com/video/BV1mY2BBTEED"
        },
        {
          "标题": "20251204 正赛 第四期 Day-3 第三局-机械狼通灵师",
          "链接": "https://www.bilibili.com/video/BV1yq2BBeEdo"
        },
        {
          "标题": "20251205 正赛 第四期 Day-4 第一局-预女猎白混",
          "链接": "https://www.bilibili.com/video/BV12k2JBEEWT"
        },
        {
          "标题": "20251205 正赛 第四期 Day-4 第二局-假面舞会",
          "链接": "https://www.bilibili.com/video/BV1xk2JBEEii"
        },
        {
          "标题": "20251205 正赛 第四期 Day-4 第三局-机械狼通灵师",
          "链接": "https://www.bilibili.com/video/BV1xk2JBEEVm"
        },
        {
          "标题": "20251209 正赛 第五期 Day-1 第一局-针锋相杠",
          "链接": "https://www.bilibili.com/video/BV1hWmHBAEpa"
        },
        {
          "标题": "20251209 正赛 第五期 Day-1 第二局-盗宝大师",
          "链接": "https://www.bilibili.com/video/BV1hWmHBAEVy"
        },
        {
          "标题": "20251209 正赛 第五期 Day-1 第三局-机械狼通灵师",
          "链接": "https://www.bilibili.com/video/BV1QWmHBAEWV"
        },
        {
          "标题": "20251210 正赛 第五期 Day-2 第一局-预女猎白混",
          "链接": "https://www.bilibili.com/video/BV1eam8BfErL"
        },
        {
          "标题": "20251210 正赛 第五期 Day-2 第二局-狼王骑士",
          "链接": "https://www.bilibili.com/video/BV1eam8BfE49"
        },
        {
          "标题": "20251210 正赛 第五期 Day-2 第三局-机械狼通灵师",
          "链接": "https://www.bilibili.com/video/BV1eam8BfEpg"
        },
        {
          "标题": "20251216 正赛 第六期 Day-1 第一局-预女猎白混",
          "链接": "https://www.bilibili.com/video/BV1GHqvB1EWn"
        },
        {
          "标题": "20251216 正赛 第六期 Day-1 第二局-假面舞会",
          "链接": "https://www.bilibili.com/video/BV1aHqvB1E85"
        },
        {
          "标题": "20251216 正赛 第六期 Day-1 第三局-机械狼通灵师",
          "链接": "https://www.bilibili.com/video/BV1GHqvB1EPj"
        },
        {
          "标题": "20251217 正赛 第六期 Day-2 第一局-预女猎白混",
          "链接": "https://www.bilibili.com/video/BV19xqjBFED8"
        },
        {
          "标题": "20251217 正赛 第六期 Day-2 第二局-盗宝大师",
          "链接": "https://www.bilibili.com/video/BV19xqjBFEpU"
        },
        {
          "标题": "20251217 正赛 第六期 Day-2 第三局-机械狼通灵师",
          "链接": "https://www.bilibili.com/video/BV19xqjBFEqN"
        },
        {
          "标题": "正片 20251218 正赛 第六期 Day-3 第一局-预女猎白混",
          "链接": "https://www.bilibili.com/video/BV1zZqDBTE2a"
        },
        {
          "标题": "正片 20251218 正赛 第六期 Day-3 第二局-假面舞会",
          "链接": "https://www.bilibili.com/video/BV1zZqDBKEbB"
        },
        {
          "标题": "正片 20251218 正赛 第六期 Day-3 第三局-机械狼通灵师",
          "链接": "https://www.bilibili.com/video/BV1zZqDBKEVm"
        },
        {
          "标题": "正片 20251218 正赛 第六期 Day-3 第四局-机械狼通灵师",
          "链接": "https://www.bilibili.com/video/BV1qwqQBYEFP"
        },
        {
          "标题": "20251219 正赛 第六期 Day-4 第一局-预女猎禁混",
          "链接": "https://www.bilibili.com/video/BV1oiqfBpEVC"
        },
        {
          "标题": "20251219 正赛 第六期 Day-4 第二局-狼美猎人",
          "链接": "https://www.bilibili.com/video/BV1qiqfBWE8G"
        },
        {
          "标题": "20251219 正赛 第六期 Day-4 第三局-机械狼通灵师",
          "链接": "https://www.bilibili.com/video/BV1oiqfBpEiq"
        },
        {
          "标题": "20251223 正赛 第七期 Day-1 第一局-预女猎白混",
          "链接": "https://www.bilibili.com/video/BV1hmBgByEbv"
        },
        {
          "标题": "20251223 正赛 第七期 Day-1 第二局-盗宝大师",
          "链接": "https://www.bilibili.com/video/BV1amBgByEgH"
        },
        {
          "标题": "20251223 正赛 第七期 Day-1 第三局-机械狼通灵师",
          "链接": "https://www.bilibili.com/video/BV1amBgByEcn"
        },
        {
          "标题": "20251224 正赛 第七期 Day-2 第一局-预女猎白混",
          "链接": "https://www.bilibili.com/video/BV1K6B1BTEdt"
        },
        {
          "标题": "20251224 正赛 第七期 Day-2 第二局-狼美人猎人",
          "链接": "https://www.bilibili.com/video/BV1m6B1BTE31"
        },
        {
          "标题": "20251224 正赛 第七期 Day-2 第三局-机械狼通灵师",
          "链接": "https://www.bilibili.com/video/BV1T6B1BTEVC"
        },
        {
          "标题": "20251225 正赛 第七期 Day-3 第一局-预女猎禁混",
          "链接": "https://www.bilibili.com/video/BV1WHB9BHEVm"
        },
        {
          "标题": "20251225 正赛 第七期 Day-3 唯邻是从",
          "链接": "https://www.bilibili.com/video/BV1WHB9BHEEF"
        },
        {
          "标题": "20251225 正赛 第七期 Day-3 机械狼通灵师",
          "链接": "https://www.bilibili.com/video/BV1WHB9BHEEN"
        },
        {
          "标题": "20251226 正赛 第七期 Day-4 第一局-预女猎白混",
          "链接": "https://www.bilibili.com/video/BV1G3BvBjEct"
        },
        {
          "标题": "20251226 正赛 第七期 Day-4 第二局-假面舞会",
          "链接": "https://www.bilibili.com/video/BV133BvBjELT"
        },
        {
          "标题": "20251226 正赛 第七期 Day-4 第三局-机械狼通灵师",
          "链接": "https://www.bilibili.com/video/BV133BvBjEdk"
        },
        {
          "标题": "20251226 正赛 第七期 Day-4 第四局-机械狼通灵师",
          "链接": "https://www.bilibili.com/video/BV133BvBjEkh"
        },
        {
          "标题": "20251230 正赛 第八期 Day-1 第一局-预女猎白混",
          "链接": "https://www.bilibili.com/video/BV1FTveBJEiv"
        },
        {
          "标题": "20251230 正赛 第八期 Day-1 第二局-盗宝大师",
          "链接": "https://www.bilibili.com/video/BV1JTveBJEkY"
        },
        {
          "标题": "20251230 正赛 第八期 Day-1 第三局-机械狼通灵师",
          "链接": "https://www.bilibili.com/video/BV1FTveBJE6R"
        },
        {
          "标题": "20251231 正赛 第八期 Day-2 第一局-预女猎白混",
          "链接": "https://www.bilibili.com/video/BV1Lyi3BUEnd"
        },
        {
          "标题": "20251231 正赛 第八期 Day-2 第二局-狼美人猎人",
          "链接": "https://www.bilibili.com/video/BV1vyi3BUERn"
        },
        {
          "标题": "20251231 正赛 第八期 Day-2 第三局-机械狼通灵师",
          "链接": "https://www.bilibili.com/video/BV1vyi3BUE4S"
        },
        {
          "标题": "20260101 正赛 第八期 Day-3 第一局-预女猎白混",
          "链接": "https://www.bilibili.com/video/BV1dSvXBaE9w"
        },
        {
          "标题": "20260101 正赛 第八期 Day-3 第二局-魔幻对决",
          "链接": "https://www.bilibili.com/video/BV1c6vXBzEYv"
        },
        {
          "标题": "20260101 正赛 第八期 Day-3 第三局-机械狼通灵师",
          "链接": "https://www.bilibili.com/video/BV1HzvXBgEFv"
        },
        {
          "标题": "20260102 正赛 第八期 Day-4 第一局-预女猎白混",
          "链接": "https://www.bilibili.com/video/BV1FGihBVEjY"
        },
        {
          "标题": "20260102 正赛 第八期 Day-4 第二局-假面舞会",
          "链接": "https://www.bilibili.com/video/BV1CAihBEE1G"
        },
        {
          "标题": "20260102 正赛 第八期 Day-4 第三局-机械狼通灵师",
          "链接": "https://www.bilibili.com/video/BV1VpihBvEiu"
        },
        {
          "标题": "20260106 正赛 第九期 Day-1 第一局-预女猎白混",
          "链接": "https://www.bilibili.com/video/BV1ikqKBBEcS"
        },
        {
          "标题": "20260106 正赛 第九期 Day-1 第二局-孤注一掷",
          "链接": "https://www.bilibili.com/video/BV1ikqKBBEcB"
        },
        {
          "标题": "20260106 正赛 第九期 Day-1 第三局-机械狼通灵师",
          "链接": "https://www.bilibili.com/video/BV1ikqKBBEY8"
        },
        {
          "标题": "20260107 正赛 第九期 Day-2 第一局-预女猎白混",
          "链接": "https://www.bilibili.com/video/BV1pvimBhEQM"
        },
        {
          "标题": "20260107 正赛 第九期 Day-2 第二局-狼美人猎人",
          "链接": "https://www.bilibili.com/video/BV1pvimBhE8F"
        },
        {
          "标题": "20260107 正赛 第九期 Day-2 第三局-机械狼通灵师",
          "链接": "https://www.bilibili.com/video/BV1pvimBhELD"
        },
        {
          "标题": "20260108 正赛 第九期 Day-3 第一局-预女猎白混",
          "链接": "https://www.bilibili.com/video/BV1ahidBKEhv"
        },
        {
          "标题": "20260108 正赛 第九期 Day-3 唯邻是从",
          "链接": "https://www.bilibili.com/video/BV1YhidBKEAh"
        },
        {
          "标题": "20260108 正赛 第九期 Day-3 机械狼通灵师",
          "链接": "https://www.bilibili.com/video/BV1ahidBKE9h"
        },
        {
          "标题": "20260109 正赛 第九期 Day-4 第一局-预女猎白混",
          "链接": "https://www.bilibili.com/video/BV1hurMBCE8k"
        },
        {
          "标题": "20260109 正赛 第九期 Day-4 第二局-假面舞会",
          "链接": "https://www.bilibili.com/video/BV1gurMByEBN"
        },
        {
          "标题": "20260109 正赛 第九期 Day-4 第三局-机械狼通灵师",
          "链接": "https://www.bilibili.com/video/BV1hurMBCExT"
        },
        {
          "标题": "20260113 正赛 第十期 Day-1 第一局-预女猎白混",
          "链接": "https://www.bilibili.com/video/BV16NrjBEEUM"
        },
        {
          "标题": "20260113 正赛 第十期 Day-1 第二局-孤注一掷",
          "链接": "https://www.bilibili.com/video/BV1FNrjBJE6S"
        },
        {
          "标题": "20260113 正赛 第十期 Day-1 第三局-机械狼通灵师",
          "链接": "https://www.bilibili.com/video/BV16NrjBEExK"
        },
        {
          "标题": "20260114 正赛 第十期 Day-2 第一局-预女猎白混",
          "链接": "https://www.bilibili.com/video/BV1csr4BjEKe"
        },
        {
          "标题": "20260114 正赛 第十期 Day-2 第二局-狼美猎人",
          "链接": "https://www.bilibili.com/video/BV16sr4BLE5B"
        },
        {
          "标题": "20260114 正赛 第十期 Day-2 第三局-机械狼通灵师",
          "链接": "https://www.bilibili.com/video/BV16sr4BLE6D"
        },
        {
          "标题": "20260115 正赛 第十期 Day-3 第一局-预女猎白混",
          "链接": "https://www.bilibili.com/video/BV1NzkwBXEPU"
        },
        {
          "标题": "20260115 正赛 第十期 Day-3 第二局-魔幻对决",
          "链接": "https://www.bilibili.com/video/BV1NBkwBWE5H"
        },
        {
          "标题": "20260115 正赛 第十期 Day-3 第三局-机械狼通灵师",
          "链接": "https://www.bilibili.com/video/BV1NBkwBWED8"
        },
        {
          "标题": "20260116 正赛 第十期 Day-4 第一局-预女猎白混",
          "链接": "https://www.bilibili.com/video/BV1AMrCBwEZP"
        },
        {
          "标题": "20260116 正赛 第十期 Day-4 第二局-唯邻是从",
          "链接": "https://www.bilibili.com/video/BV1WMrCBwE7L"
        },
        {
          "标题": "20260116 正赛 第十期 Day-4 第三局-机械狼通灵师",
          "链接": "https://www.bilibili.com/video/BV1AMrCBwECC"
        },
        {
          "标题": "20260120 正赛 第十一期 Day-1 第一局-预女猎白混",
          "链接": "https://www.bilibili.com/video/BV17UknBbEnP"
        },
        {
          "标题": "20260120 正赛 第十一期 Day-1 第二局-魔幻对决",
          "链接": "https://www.bilibili.com/video/BV17UknBbE3E"
        },
        {
          "标题": "20260120 正赛 第十一期 Day-1 第三局-机械狼通灵师",
          "链接": "https://www.bilibili.com/video/BV1jUknBbEyy"
        },
        {
          "标题": "20260121 正赛 第十一期 Day-2 第一局-预女猎白混",
          "链接": "https://www.bilibili.com/video/BV1WAz7BQEB1"
        },
        {
          "标题": "20260121 正赛 第十一期 Day-2 第二局-唯邻是从",
          "链接": "https://www.bilibili.com/video/BV1CAz7BQEyv"
        },
        {
          "标题": "20260121 正赛 第十一期 Day-2 第三局-机械狼通灵师",
          "链接": "https://www.bilibili.com/video/BV1CAz7BQE4w"
        },
        {
          "标题": "20260122 正赛 第十一期 Day-3 第一局-预女猎白混",
          "链接": "https://www.bilibili.com/video/BV1w7zcBMECN"
        },
        {
          "标题": "20260122 正赛 第十一期 Day-3 第二局-盗宝大师",
          "链接": "https://www.bilibili.com/video/BV1p7zcBMEAj"
        },
        {
          "标题": "20260122 正赛 第十一期 Day-3 第三局-机械狼通灵师",
          "链接": "https://www.bilibili.com/video/BV1w7zcBMET2"
        },
        {
          "标题": "20260123 正赛 第十一期 Day-4 第一局-预女猎白混",
          "链接": "https://www.bilibili.com/video/BV1G3zuB5E6r"
        },
        {
          "标题": "20260123 正赛 第十一期 Day-4 第二局-假面舞会",
          "链接": "https://www.bilibili.com/video/BV1Y3zuB5EVD"
        },
        {
          "标题": "20260123 正赛 第十一期 Day-4 第三局-机械狼通灵师",
          "链接": "https://www.bilibili.com/video/BV1Y3zuB5Eup"
        },
        {
          "标题": "20260127 决赛 Day-1 第一局-预女猎白混",
          "链接": "https://www.bilibili.com/video/BV1ii63BfEdD"
        },
        {
          "标题": "20260127 决赛 Day-1 第二局-孤注一掷",
          "链接": "https://www.bilibili.com/video/BV1oi63BZEwz"
        },
        {
          "标题": "20260127 决赛 Day-1 第三局-机械狼通灵师",
          "链接": "https://www.bilibili.com/video/BV1ov63BbEFv"
        },
        {
          "标题": "20260128 决赛 Day-2 第一局-预女猎白混",
          "链接": "https://www.bilibili.com/video/BV12HzXBxEer"
        },
        {
          "标题": "20260128 决赛 Day-2 第二局-盗宝大师",
          "链接": "https://www.bilibili.com/video/BV12HzXBxEez"
        },
        {
          "标题": "20260128 决赛 Day-2 第三局-机械狼通灵师",
          "链接": "https://www.bilibili.com/video/BV14HzXB4Ei1"
        },
        {
          "标题": "20260129 决赛 Day-3 第一局-预女猎白混",
          "链接": "https://www.bilibili.com/video/BV1wQ6AB2Ect"
        },
        {
          "标题": "20260129 决赛 Day-3 第二局-盗宝大师",
          "链接": "https://www.bilibili.com/video/BV1rQ6AB1Ejf"
        },
        {
          "标题": "20260129 决赛 Day-3 第三局-机械狼通灵师",
          "链接": "https://www.bilibili.com/video/BV1rQ6AB1EHt"
        },
        {
          "标题": "20260130 决赛 Day-4 第一局-预女猎白混",
          "链接": "https://www.bilibili.com/video/BV1fn6zBkEUn"
        },
        {
          "标题": "20260130 决赛 Day-4 第二局-假面舞会",
          "链接": "https://www.bilibili.com/video/BV1En6zBCEXR"
        },
        {
          "标题": "20260130 决赛 Day-4 第三局-机械狼通灵师",
          "链接": "https://www.bilibili.com/video/BV1fn6zBkEmF"
        },
        {
          "标题": "20260130 决赛颁奖",
          "链接": "https://www.bilibili.com/video/BV1fn6zBkEYQ"
        }
      ]
    },
    {
      "来源": "https://space.bilibili.com/19106800/lists/7520632?type=season",
      "mid": 19106800,
      "合集ID": 7520632,
      "合集标题": "傀趣奇谭",
      "视频": [
        {
          "标题": "20260224 表演赛 Day-1 第一局-预女猎白混",
          "链接": "https://www.bilibili.com/video/BV15EfUBrENW"
        },
        {
          "标题": "20260224 表演赛 Day-1 第二局-狼王守卫",
          "链接": "https://www.bilibili.com/video/BV1XEfUB6Equ"
        },
        {
          "标题": "20260224 表演赛 Day-1 第三局-狼王骑士",
          "链接": "https://www.bilibili.com/video/BV19EfUB6EhR"
        },
        {
          "标题": "20260225 表演赛 Day-2 第一局-预女猎白混",
          "链接": "https://www.bilibili.com/video/BV1f5f8BhEXc"
        },
        {
          "标题": "20260225 表演赛 Day-2 第二局-盗宝大师",
          "链接": "https://www.bilibili.com/video/BV1f5f8BhEKS"
        },
        {
          "标题": "20260225 表演赛 Day-2 第三局-机械狼通灵师",
          "链接": "https://www.bilibili.com/video/BV1z5f8BhE5j"
        },
        {
          "标题": "20260226 表演赛 Day-3 第一局-预女猎白混",
          "链接": "https://www.bilibili.com/video/BV1CBArzEE1s"
        },
        {
          "标题": "20260226 表演赛 Day-3 第二局-假面舞会",
          "链接": "https://www.bilibili.com/video/BV1yBArzEEyk"
        },
        {
          "标题": "20260226 表演赛 Day-3 第三局-机械狼通灵师",
          "链接": "https://www.bilibili.com/video/BV1yBArzEEAd"
        },
        {
          "标题": "20260227 表演赛 Day-4 第一局-预女猎白混",
          "链接": "https://www.bilibili.com/video/BV161AXzVEmV"
        },
        {
          "标题": "20260227 表演赛 Day-4 第二局-盗宝大师",
          "链接": "https://www.bilibili.com/video/BV1r1AXzVEDm"
        },
        {
          "标题": "20260227 表演赛 Day-4 第三局-机械狼通灵师",
          "链接": "https://www.bilibili.com/video/BV1H1AXzVE7Y"
        },
        {
          "标题": "20260303 正赛 第一期 Day-1 第一局-预女猎白混",
          "链接": "https://www.bilibili.com/video/BV1juPwzfEj5"
        },
        {
          "标题": "20260303 正赛 第一期 Day-1 第二局-假面舞会",
          "链接": "https://www.bilibili.com/video/BV1juPwzfEQL"
        },
        {
          "标题": "20260303 正赛 第一期 Day-1 第三局-机械狼通灵师",
          "链接": "https://www.bilibili.com/video/BV1juPwzfEgi"
        },
        {
          "标题": "20260303 正赛 第一期 Day-1 第四局-机械狼通灵师",
          "链接": "https://www.bilibili.com/video/BV1nwPwzeEWx"
        },
        {
          "标题": "20260304 正赛 Day-2 第一局-预女猎白混",
          "链接": "https://www.bilibili.com/video/BV1SMPqzjExw"
        },
        {
          "标题": "20260304 正赛 Day-2 第二局-唯邻是从",
          "链接": "https://www.bilibili.com/video/BV1SMPqzjEe6"
        },
        {
          "标题": "20260304 正赛 Day-2 第三局-机械狼通灵师",
          "链接": "https://www.bilibili.com/video/BV1UMPqzjEvH"
        },
        {
          "标题": "20260305 正赛 Day-3 第一局-预女猎白混",
          "链接": "https://www.bilibili.com/video/BV14UPyzAEhn"
        },
        {
          "标题": "20260305 正赛 Day-3 第二局-盗宝大师",
          "链接": "https://www.bilibili.com/video/BV1TUPyzAEwW"
        },
        {
          "标题": "20260305 正赛 Day-3 第三局-机械狼通灵师",
          "链接": "https://www.bilibili.com/video/BV1KUPyzAETp"
        },
        {
          "标题": "20260306 正赛 Day-4 第一局-预女猎白混",
          "链接": "https://www.bilibili.com/video/BV1MMPxzmEps"
        },
        {
          "标题": "20260306 正赛 Day-4 第二局-孤注一掷",
          "链接": "https://www.bilibili.com/video/BV1MMPxzmEWJ"
        },
        {
          "标题": "20260306 正赛 Day-4 第三局-机械狼通灵师",
          "链接": "https://www.bilibili.com/video/BV1uMPxzmEtV"
        },
        {
          "标题": "20260310 正赛 第二期 Day-1 第一局-预女猎白混",
          "链接": "https://www.bilibili.com/video/BV1Vsc9zfEJv"
        },
        {
          "标题": "20260310 正赛 第二期 Day-1 第二局-狼王守卫",
          "链接": "https://www.bilibili.com/video/BV1Gsc9zfEmb"
        },
        {
          "标题": "20260310 正赛 第二期 Day-1 第三局-机械狼通灵师",
          "链接": "https://www.bilibili.com/video/BV1Vsc9zfEJt"
        },
        {
          "标题": "20260311 正赛 第二期 Day-2 第一局-预女猎白混",
          "链接": "https://www.bilibili.com/video/BV1ZGwAzZEny"
        },
        {
          "标题": "20260311 正赛 第二期 Day-2 唯邻是从",
          "链接": "https://www.bilibili.com/video/BV1oGwAzZEyW"
        },
        {
          "标题": "20260311 正赛 第二期 Day-2 第三局-机械狼通灵师",
          "链接": "https://www.bilibili.com/video/BV1oGwAzZEXf"
        },
        {
          "标题": "20260312 正赛 第二期 Day-3 第一局-预女猎白混",
          "链接": "https://www.bilibili.com/video/BV1FacCz5EyR"
        },
        {
          "标题": "20260312 正赛 第二期 Day-3 第二局-假面舞会",
          "链接": "https://www.bilibili.com/video/BV1nacCz5EDV"
        },
        {
          "标题": "20260312 正赛 第二期 Day-3 第三局-机械狼通灵师",
          "链接": "https://www.bilibili.com/video/BV1FacCz5E9e"
        },
        {
          "标题": "20260312 正赛 第二期 Day-3 第四局-机械狼通灵师",
          "链接": "https://www.bilibili.com/video/BV1HacCz5EMk"
        },
        {
          "标题": "20260313 正赛 第二期 Day-4 第一局-预女猎白混",
          "链接": "https://www.bilibili.com/video/BV1XawEzcEGc"
        },
        {
          "标题": "20260313 正赛 第二期 Day-4 第二局-盗宝大师",
          "链接": "https://www.bilibili.com/video/BV1aawEzcEeP"
        },
        {
          "标题": "20260313 正赛 第二期 Day-4 第三局-机械狼通灵师",
          "链接": "https://www.bilibili.com/video/BV1aawEzcEeM"
        },
        {
          "标题": "20260317 正赛 第三期 Day-1 第一局-预女猎白混",
          "链接": "https://www.bilibili.com/video/BV1Xdw9zhEsh"
        },
        {
          "标题": "20260317 正赛 第三期 Day-1 第二局-假面舞会",
          "链接": "https://www.bilibili.com/video/BV1LUw9zTEZT"
        },
        {
          "标题": "20260317 正赛 第三期 Day-1 第三局-机械狼通灵师",
          "链接": "https://www.bilibili.com/video/BV1dUw9zKExP"
        },
        {
          "标题": "20260318 正赛 第三期 Day-2 第一局-预女猎白混",
          "链接": "https://www.bilibili.com/video/BV1U5wBz5EEs"
        },
        {
          "标题": "20260318 正赛 第三期 Day-2 第二局-诡术之境",
          "链接": "https://www.bilibili.com/video/BV1b5wBz5E6T"
        },
        {
          "标题": "20260318 正赛 第三期 Day-2 第三局-机械狼通灵师",
          "链接": "https://www.bilibili.com/video/BV1b5wBz5Exk"
        },
        {
          "标题": "20260319 正赛 第三期 Day-3 第一局-预女猎白混",
          "链接": "https://www.bilibili.com/video/BV1w3AVzPEZM"
        },
        {
          "标题": "20260319 正赛 第三期 Day-3 第二局-盗宝大师",
          "链接": "https://www.bilibili.com/video/BV1w3AVzPEAL"
        },
        {
          "标题": "20260319 正赛 第三期 Day-3 第三局-机械狼通灵师",
          "链接": "https://www.bilibili.com/video/BV1w3AVzPE3R"
        },
        {
          "标题": "20260320 正赛 第三期 Day-4 第一局-预女猎白混",
          "链接": "https://www.bilibili.com/video/BV1XyAHzkE9U"
        },
        {
          "标题": "20260320 正赛 第三期 Day-4 第二局-诡术之境",
          "链接": "https://www.bilibili.com/video/BV1VyAHzCENA"
        },
        {
          "标题": "20260320 正赛 第三期 Day-4 第三局-机械狼通灵师",
          "链接": "https://www.bilibili.com/video/BV1XyAHzkE1w"
        },
        {
          "标题": "20260324 正赛 第四期 Day-1 第一局-预女猎白混",
          "链接": "https://www.bilibili.com/video/BV1ufQkBeEYL"
        },
        {
          "标题": "20260324 正赛 第四期 Day-1 第二局-假面舞会",
          "链接": "https://www.bilibili.com/video/BV1MfQkBeEmP"
        },
        {
          "标题": "20260324 正赛 第四期 Day-1 第三局-机械狼通灵师",
          "链接": "https://www.bilibili.com/video/BV1MfQkBeEmg"
        },
        {
          "标题": "20260325 正赛 第四期 Day-2 第一局-预女猎白混",
          "链接": "https://www.bilibili.com/video/BV1roX7BQEfa"
        },
        {
          "标题": "20260325 正赛 第四期 Day-2 第三局-机械狼通灵师",
          "链接": "https://www.bilibili.com/video/BV1roX7BQEau"
        },
        {
          "标题": "20260325 正赛 第四期 Day-2 第二局-唯邻是从",
          "链接": "https://www.bilibili.com/video/BV1roX7BQE1n"
        },
        {
          "标题": "20260326 正赛 第四期 Day-3 第一局-预女猎白混",
          "链接": "https://www.bilibili.com/video/BV1udXxBxEX7"
        },
        {
          "标题": "20260326 正赛 第四期 Day-3 第二局-诡术之境",
          "链接": "https://www.bilibili.com/video/BV1cLX4BkETh"
        },
        {
          "标题": "20260327 正赛 第四期 Day-4 第一局-预女猎白混",
          "链接": "https://www.bilibili.com/video/BV18NXgB5E8k"
        },
        {
          "标题": "20260327 正赛 第四期 Day-4 第三局-机械狼通灵师",
          "链接": "https://www.bilibili.com/video/BV1hNXgB5Ewp"
        },
        {
          "标题": "20260327 正赛 第四期 Day-4 第二局-盗宝大师",
          "链接": "https://www.bilibili.com/video/BV1hAXgB1ECp"
        },
        {
          "标题": "20260331 正赛 第五期 Day-1 第一局-预女猎白混",
          "链接": "https://www.bilibili.com/video/BV1j8XkB7EUD"
        },
        {
          "标题": "20260331 正赛 第五期 Day-1 第二局-孤注一掷",
          "链接": "https://www.bilibili.com/video/BV178XkB7EXx"
        },
        {
          "标题": "20260331 正赛 第五期 Day-1 第三局-机械狼通灵师",
          "链接": "https://www.bilibili.com/video/BV178XkB7ECz"
        },
        {
          "标题": "20260401 正赛 第五期 Day-2 第一局-预女猎白混",
          "链接": "https://www.bilibili.com/video/BV1NP9HBBEDj"
        },
        {
          "标题": "20260401 正赛 第五期 Day-2 第二局-诡术之境",
          "链接": "https://www.bilibili.com/video/BV1NP9HBBEKw"
        },
        {
          "标题": "20260401 正赛 第五期 Day-2 第三局-机械狼通灵师",
          "链接": "https://www.bilibili.com/video/BV1KP9HBBEcN"
        },
        {
          "标题": "20260402 正赛 第五期 Day-3 第一局-预女猎白混",
          "链接": "https://www.bilibili.com/video/BV1Zy9wBBE1P"
        },
        {
          "标题": "20260402 正赛 第五期 Day-3 第二局-唯邻是从",
          "链接": "https://www.bilibili.com/video/BV1Ey9wBzEEV"
        },
        {
          "标题": "20260402 正赛 第五期 Day-3 第三局-机械狼通灵师",
          "链接": "https://www.bilibili.com/video/BV1fy9wBBEAq"
        },
        {
          "标题": "20260403 正赛 第五期 Day-4 第一局-预女猎白混",
          "链接": "https://www.bilibili.com/video/BV17J9gBZEb8"
        },
        {
          "标题": "20260403 正赛 第五期 Day-4 第二局-盗宝大师",
          "链接": "https://www.bilibili.com/video/BV17J9gBZEJy"
        },
        {
          "标题": "20260403 正赛 第五期 Day-4 第三局-机械狼通灵师",
          "链接": "https://www.bilibili.com/video/BV1qJ9gBZEU8"
        },
        {
          "标题": "20260407 正赛 第六期 Day-1 第一局-预女猎白混",
          "链接": "https://www.bilibili.com/video/BV1W8DiBKEYM"
        },
        {
          "标题": "20260407 正赛 第六期 Day-1 第二局-诡术之境",
          "链接": "https://www.bilibili.com/video/BV1W8DiBKE66"
        },
        {
          "标题": "20260407 正赛 第六期 Day-1 第三局-机械狼通灵师",
          "链接": "https://www.bilibili.com/video/BV1W8DiBKEhd"
        },
        {
          "标题": "20260407 正赛 第六期 Day-1 第四局-诡术之境",
          "链接": "https://www.bilibili.com/video/BV1A8DiBTECq"
        },
        {
          "标题": "20260408 正赛 第六期 Day-2 第一局-预女猎白混",
          "链接": "https://www.bilibili.com/video/BV17MD7BBE7Z"
        },
        {
          "标题": "20260408 正赛 第六期 Day-2 第二局-诡术之境",
          "链接": "https://www.bilibili.com/video/BV17MD7BzEv9"
        },
        {
          "标题": "20260408 正赛 第六期 Day-2 第三局-机械狼通灵师",
          "链接": "https://www.bilibili.com/video/BV17MD7BBE4v"
        },
        {
          "标题": "20260409 正赛 第六期 Day-3 第一局-预女猎白混",
          "链接": "https://www.bilibili.com/video/BV1ViDtBFE1W"
        },
        {
          "标题": "20260409 正赛 第六期 Day-3 第二局-盗宝大师",
          "链接": "https://www.bilibili.com/video/BV1ViDtBFE1n"
        },
        {
          "标题": "20260409 正赛 第六期 Day-3 第三局-机械狼通灵师",
          "链接": "https://www.bilibili.com/video/BV1GiDtBFErB"
        },
        {
          "标题": "20260410 正赛 第六期 Day-4 第一局-预女猎白混",
          "链接": "https://www.bilibili.com/video/BV11vQAB2EwD"
        },
        {
          "标题": "20260410 正赛 第六期 Day-4 第二局-假面舞会",
          "链接": "https://www.bilibili.com/video/BV1NvQABmEhe"
        },
        {
          "标题": "20260410 正赛 第六期 Day-4 第三局-机械狼通灵师",
          "链接": "https://www.bilibili.com/video/BV11vQAB2ELZ"
        },
        {
          "标题": "20260414 正赛 第七期 Day-1 第一局-预女猎白混",
          "链接": "https://www.bilibili.com/video/BV16EQ3BhEe4"
        },
        {
          "标题": "20260414 正赛 第七期 Day-1 第二局-诡术之境",
          "链接": "https://www.bilibili.com/video/BV1cEQ3BhEMe"
        },
        {
          "标题": "20260414 正赛 第七期 Day-1 第三局-机械狼通灵师",
          "链接": "https://www.bilibili.com/video/BV1cEQ3BhEpC"
        },
        {
          "标题": "20260414 正赛 第七期 Day-1 第四局-诡术之境",
          "链接": "https://www.bilibili.com/video/BV1FEQ3BhEqY"
        },
        {
          "标题": "20260415 正赛 第七期 Day-2 第一局-预女猎白混",
          "链接": "https://www.bilibili.com/video/BV1fBQJBUEwd"
        },
        {
          "标题": "20260415 正赛 第七期 Day-2 第二局-诡术之境",
          "链接": "https://www.bilibili.com/video/BV1ZBQJBUEZJ"
        },
        {
          "标题": "20260415 正赛 第七期 Day-2 第三局-机械狼通灵师",
          "链接": "https://www.bilibili.com/video/BV1fBQJBUEnp"
        },
        {
          "标题": "20260416 正赛 第七期 Day-3 第一局-预女猎白混",
          "链接": "https://www.bilibili.com/video/BV16ddeBMEWW"
        },
        {
          "标题": "20260416 正赛 第七期 Day-3 第二局-盗宝大师",
          "链接": "https://www.bilibili.com/video/BV1zddeBMEBn"
        },
        {
          "标题": "20260416 正赛 第七期 Day-3 第三局-机械狼通灵师",
          "链接": "https://www.bilibili.com/video/BV16ddeBMEW7"
        },
        {
          "标题": "20260417 正赛 第七期 Day-4 第一局-预女猎白混",
          "链接": "https://www.bilibili.com/video/BV1CGdLBREUY"
        },
        {
          "标题": "20260417 正赛 第七期 Day-4 第二局-假面舞会",
          "链接": "https://www.bilibili.com/video/BV1sGdLBdEPX"
        },
        {
          "标题": "20260417 正赛 第七期 Day-4 第三局-机械狼通灵师",
          "链接": "https://www.bilibili.com/video/BV1CGdLBREUE"
        },
        {
          "标题": "20260421 正赛 第八期 Day-1 第一局-预女猎白混",
          "链接": "https://www.bilibili.com/video/BV16NdDB7ETc"
        },
        {
          "标题": "20260421 正赛 第八期 Day-1 第二局-诡术之境",
          "链接": "https://www.bilibili.com/video/BV1ENdDB7Emb"
        },
        {
          "标题": "20260421 正赛 第八期 Day-1 第三局-机械狼通灵师",
          "链接": "https://www.bilibili.com/video/BV16NdDB7E3b"
        },
        {
          "标题": "20260422 正赛 第八期 Day-2 第二局-诡术之境",
          "链接": "https://www.bilibili.com/video/BV1ayoxBqEyr"
        },
        {
          "标题": "20260422 正赛 第八期 Day-2 第三局-机械狼通灵师",
          "链接": "https://www.bilibili.com/video/BV1QyoxBqEdA"
        },
        {
          "标题": "20260423 正赛 第八期 Day-3 第二局-盗宝大师",
          "链接": "https://www.bilibili.com/video/BV1otogBAE42"
        },
        {
          "标题": "20260423 正赛 第八期 Day-3 第三局-机械狼通灵师",
          "链接": "https://www.bilibili.com/video/BV1dtogBAED7"
        },
        {
          "标题": "20260424 正赛 第八期 Day-4 第一局-预女猎白混",
          "链接": "https://www.bilibili.com/video/BV19UoEBDEt1"
        },
        {
          "标题": "20260424 正赛 第八期 Day-4 第二局-假面舞会",
          "链接": "https://www.bilibili.com/video/BV19UoEBDEcH"
        },
        {
          "标题": "20260424 正赛 第八期 Day-4 第三局-机械狼通灵师",
          "链接": "https://www.bilibili.com/video/BV1XUoEBDEYD"
        },
        {
          "标题": "20260429 正赛 第九期 Day-1 第二局-盗宝大师",
          "链接": "https://www.bilibili.com/video/BV1iQ9sBAEwq"
        },
        {
          "标题": "20260429 正赛 第九期 Day-1 第三局-机械狼通灵师",
          "链接": "https://www.bilibili.com/video/BV1LQ9sBAEkn"
        },
        {
          "标题": "20260430 正赛 第九期 Day-2 第一局-预女猎白混",
          "链接": "https://www.bilibili.com/video/BV1JC9iBMEZw"
        },
        {
          "标题": "20260430 正赛 第九期 Day-2 第三局-机械狼通灵师",
          "链接": "https://www.bilibili.com/video/BV1FC9iBMEqk"
        },
        {
          "标题": "20260501 正赛 第九期 Day-3 第一局-预女猎白混",
          "链接": "https://www.bilibili.com/video/BV1tDR3BJEz3"
        },
        {
          "标题": "20260501 正赛 第九期 Day-3 第二局-假面舞会",
          "链接": "https://www.bilibili.com/video/BV1tDR3BJE8x"
        },
        {
          "标题": "20260501 正赛 第九期 Day-3 第三局-机械狼通灵师",
          "链接": "https://www.bilibili.com/video/BV14DR3BJEyL"
        },
        {
          "标题": "20260505 正赛 第十期 Day-1 第一局-预女猎白混",
          "链接": "https://www.bilibili.com/video/BV1jURJB9Eao"
        },
        {
          "标题": "20260505 正赛 第十期 Day-1 第二局-盗宝大师",
          "链接": "https://www.bilibili.com/video/BV1iURJBXExP"
        },
        {
          "标题": "20260505 正赛 第十期 Day-1 第三局-机械狼通灵师",
          "链接": "https://www.bilibili.com/video/BV1iURJBXETp"
        },
        {
          "标题": "20260506 正赛 第十期 Day-2 第一局-预女猎白混",
          "链接": "https://www.bilibili.com/video/BV1wgRtBQEms"
        },
        {
          "标题": "20260506 正赛 第十期 Day-2 第二局-诡术之境",
          "链接": "https://www.bilibili.com/video/BV1wgRtBQEmG"
        },
        {
          "标题": "20260507 特辑 京师和Ta的朋友们 第一局-预女猎白",
          "链接": "https://www.bilibili.com/video/BV1PjdKBwEYg"
        },
        {
          "标题": "20260507 特辑 京师和Ta的朋友们 第二局-黑狼王骑士",
          "链接": "https://www.bilibili.com/video/BV1AjdKBwEmT"
        },
        {
          "标题": "20260507 特辑 京师和Ta的朋友们 第三局-趣味狼人杀",
          "链接": "https://www.bilibili.com/video/BV1PjdKBwEkA"
        },
        {
          "标题": "20260508 正赛 第十期 Day-4 第一局-预女猎白混",
          "链接": "https://www.bilibili.com/video/BV1DMRmB9EQR"
        },
        {
          "标题": "20260508 正赛 第十期 Day-4 第三局-机械狼通灵师",
          "链接": "https://www.bilibili.com/video/BV1QMRmB9Ecv"
        },
        {
          "标题": "20260508 正赛 第十期 Day-4 第二局-假面舞会",
          "链接": "https://www.bilibili.com/video/BV1DMRmB9Evw"
        },
        {
          "标题": "20260512 决赛 Day-1 第一局-预女猎白混",
          "链接": "https://www.bilibili.com/video/BV1fS536BEUq"
        },
        {
          "标题": "20260512 决赛 Day-1 第三局-机械狼通灵师",
          "链接": "https://www.bilibili.com/video/BV1FS536zEwq"
        },
        {
          "标题": "20260513 决赛 Day-2 第一局-预女猎白混",
          "链接": "https://www.bilibili.com/video/BV1Bi526NEQk"
        },
        {
          "标题": "20260513 决赛 Day-2 第二局-诡术之境",
          "链接": "https://www.bilibili.com/video/BV1Zi526NEUU"
        },
        {
          "标题": "20260513 决赛 Day-2 第三局-机械狼通灵师",
          "链接": "https://www.bilibili.com/video/BV1Bi526NEYo"
        },
        {
          "标题": "20260514 决赛 Day-3 第一局-预女猎白混",
          "链接": "https://www.bilibili.com/video/BV1U85R63Ev5"
        },
        {
          "标题": "20260514 决赛 Day-3 第二局-盗宝大师",
          "链接": "https://www.bilibili.com/video/BV1U85R63EM6"
        },
        {
          "标题": "20260515 决赛 Day-4 第一局-预女猎白混",
          "链接": "https://www.bilibili.com/video/BV1un5z6AEBQ"
        },
        {
          "标题": "20260515 决赛 Day-4 第二局-唯邻是从",
          "链接": "https://www.bilibili.com/video/BV18n5z6AEAt"
        },
        {
          "标题": "20260515 决赛 Day-4 第三局-机械狼通灵师",
          "链接": "https://www.bilibili.com/video/BV1un5z6AEKX"
        }
      ]
    },
    {
      "来源": "https://space.bilibili.com/19106800/lists/8209896?type=season",
      "mid": 19106800,
      "合集ID": 8209896,
      "合集标题": "曙光航纪",
      "视频": [
        {
          "标题": "20260526 表演赛 Day-1 第一局-预女猎白混",
          "链接": "https://www.bilibili.com/video/BV1iJVT6SEL2"
        },
        {
          "标题": "20260526 表演赛 Day-1 第二局-狼王守卫",
          "链接": "https://www.bilibili.com/video/BV1jJVT6SEN4"
        },
        {
          "标题": "20260526 表演赛 Day-1 第三局-狼王骑士",
          "链接": "https://www.bilibili.com/video/BV1jJVT6SEWc"
        },
        {
          "标题": "20260527 表演赛 Day-2 第一局-预女猎白混",
          "链接": "https://www.bilibili.com/video/BV1kdGU6GEsq"
        },
        {
          "标题": "20260527 表演赛 Day-2 第二局-假面舞会",
          "链接": "https://www.bilibili.com/video/BV1rdGU6GEXm"
        },
        {
          "标题": "20260527 表演赛 Day-2 第三局-机械狼通灵师",
          "链接": "https://www.bilibili.com/video/BV1rdGU6GEXi"
        },
        {
          "标题": "20260528 表演赛 Day-3 第二局-诡术之境",
          "链接": "https://www.bilibili.com/video/BV1qKVW6YEZu"
        },
        {
          "标题": "20260528 表演赛 Day-3 第三局-机械狼通灵师",
          "链接": "https://www.bilibili.com/video/BV1BKVW6YE8u"
        },
        {
          "标题": "20260529 表演赛 Day-4 第一局-预女猎白混",
          "链接": "https://www.bilibili.com/video/BV1v8Ve6oEZP"
        },
        {
          "标题": "20260529 表演赛 Day-4 第二局-盗宝大师",
          "链接": "https://www.bilibili.com/video/BV1v8Ve6oEvR"
        },
        {
          "标题": "20260529 表演赛 Day-4 第三局-机械狼通灵师",
          "链接": "https://www.bilibili.com/video/BV1v8Ve6oEic"
        },
        {
          "标题": "20260602 正赛 第一期 Day-1 第一局-预女猎白混",
          "链接": "https://www.bilibili.com/video/BV1kGVC6cEyg"
        },
        {
          "标题": "20260602 正赛 第一期 Day-1 第二局-盗宝大师",
          "链接": "https://www.bilibili.com/video/BV1CGVC6cE8T"
        },
        {
          "标题": "20260602 正赛 第一期 Day-1 第三局-机械狼通灵师",
          "链接": "https://www.bilibili.com/video/BV1pGVC6cEbW"
        },
        {
          "标题": "20260603 正赛 第一期 Day-2 第一局-预女猎白混",
          "链接": "https://www.bilibili.com/video/BV1hb7R6XEtD"
        },
        {
          "标题": "20260603 正赛 第一期 Day-2 第二局-假面舞会",
          "链接": "https://www.bilibili.com/video/BV1vH7R6tEQp"
        },
        {
          "标题": "20260603 正赛 第一期 Day-2 第三局-机械狼通灵师",
          "链接": "https://www.bilibili.com/video/BV1dJ7R6fEUw"
        },
        {
          "标题": "20260604 正赛 第一期 Day-3 第一局-预女猎白混",
          "链接": "https://www.bilibili.com/video/BV12GEA6iEx5"
        },
        {
          "标题": "20260604 正赛 第一期 Day-3 第二局-盗宝大师",
          "链接": "https://www.bilibili.com/video/BV117EA6AEcV"
        },
        {
          "标题": "20260605 正赛 第一期 Day-4 第一局-预女猎白混",
          "链接": "https://www.bilibili.com/video/BV1FX7C6BEAC"
        },
        {
          "标题": "20260605 正赛 第一期 Day-4 第二局-假面舞会",
          "链接": "https://www.bilibili.com/video/BV1fX7C6qESY"
        },
        {
          "标题": "20260605 正赛 第一期 Day-4 第三局-机械狼通灵师",
          "链接": "https://www.bilibili.com/video/BV1zX7C6qEmR"
        },
        {
          "标题": "20260609 正赛 第二期 Day-1 第一局-预女猎白混",
          "链接": "https://www.bilibili.com/video/BV1iaE26kE1w"
        },
        {
          "标题": "20260609 正赛 第二期 Day-1 第二局-盗宝大师",
          "链接": "https://www.bilibili.com/video/BV1jaE26kELR"
        },
        {
          "标题": "20260609 正赛 第二期 Day-1 第三局-机械狼通灵师",
          "链接": "https://www.bilibili.com/video/BV1jaE26kE8T"
        },
        {
          "标题": "20260610 正赛 第二期 Day-2 第一局-预女猎白混",
          "链接": "https://www.bilibili.com/video/BV1xYEo6QE3H"
        },
        {
          "标题": "20260610 正赛 第二期 Day-2 第二局-假面舞会",
          "链接": "https://www.bilibili.com/video/BV1xYEo6QE3E"
        },
        {
          "标题": "20260610 正赛 第二期 Day-2 第四局-机械狼通灵师",
          "链接": "https://www.bilibili.com/video/BV1xYEo6QEGV"
        },
        {
          "标题": "20260610 正赛 第二期 Day-2 第三局-机械狼通灵师",
          "链接": "https://www.bilibili.com/video/BV1sYEo6QEyS"
        },
        {
          "标题": "20260611 正赛 第二期 Day-3 第一局-预女猎白混",
          "链接": "https://www.bilibili.com/video/BV13tEB6VE1J"
        },
        {
          "标题": "20260611 正赛 第二期 Day-3 第二局-诡术之境",
          "链接": "https://www.bilibili.com/video/BV13tEB6VEVV"
        },
        {
          "标题": "20260611 正赛 第二期 Day-3 第三局-机械狼通灵师",
          "链接": "https://www.bilibili.com/video/BV1uaEB66E7q"
        },
        {
          "标题": "20260611 正赛 第二期 Day-3 第四局-机械狼通灵师",
          "链接": "https://www.bilibili.com/video/BV1wmEB68Exu"
        },
        {
          "标题": "20260612 正赛 第二期 Day-4 第一局-预女猎白混",
          "链接": "https://www.bilibili.com/video/BV1sKJ56PEey"
        },
        {
          "标题": "20260612 正赛 第二期 Day-4 唯邻是从",
          "链接": "https://www.bilibili.com/video/BV1yKJ56PEak"
        },
        {
          "标题": "20260612 正赛 第二期 Day-4 第三局-机械狼通灵师",
          "链接": "https://www.bilibili.com/video/BV11KJ56PEPY"
        },
        {
          "标题": "20260616 正赛 第三期 Day-1 第一局-预女猎白混",
          "链接": "https://www.bilibili.com/video/BV1W6jG6HEeT"
        },
        {
          "标题": "20260616 正赛 第三期 Day-1 第二局-诡术之境",
          "链接": "https://www.bilibili.com/video/BV1W6jG6HELj"
        },
        {
          "标题": "20260616 正赛 第三期 Day-1 第三局-机械狼通灵师",
          "链接": "https://www.bilibili.com/video/BV1W6jG6HEkC"
        },
        {
          "标题": "20260617 正赛 第三期 Day-2 第一局-预女猎白混",
          "链接": "https://www.bilibili.com/video/BV1KkL96MEuH"
        },
        {
          "标题": "20260617 正赛 第三期 Day-2 第二局-假面舞会",
          "链接": "https://www.bilibili.com/video/BV1KkL96MEim"
        },
        {
          "标题": "20260617 正赛 第三期 Day-2 第三局-机械狼通灵师",
          "链接": "https://www.bilibili.com/video/BV1xkL96MEsd"
        },
        {
          "标题": "20260618 正赛 第三期 Day-3 第一局-预女猎白混",
          "链接": "https://www.bilibili.com/video/BV1Ajja66EuC"
        },
        {
          "标题": "20260618 正赛 第三期 Day-3 第二局-诡术之境",
          "链接": "https://www.bilibili.com/video/BV1Hjja6zEZa"
        },
        {
          "标题": "20260618 正赛 第三期 Day-3 第三局-机械狼通灵师",
          "链接": "https://www.bilibili.com/video/BV1Wjja66EFz"
        },
        {
          "标题": "20260619 正赛 第三期 Day-4 第一局-预女猎白混",
          "链接": "https://www.bilibili.com/video/BV17kj669ED5"
        },
        {
          "标题": "20260619 正赛 第三期 Day-4 第二局-盗宝大师",
          "链接": "https://www.bilibili.com/video/BV1Hej66FE1Y"
        },
        {
          "标题": "20260619 正赛 第三期 Day-4 第三局-机械狼通灵师",
          "链接": "https://www.bilibili.com/video/BV1nBj664EFS"
        },
        {
          "标题": "20260623 正赛 第四期 Day-1 第一局-预女猎白混",
          "链接": "https://www.bilibili.com/video/BV18ijD6BExh"
        },
        {
          "标题": "20260623 正赛 第四期 Day-1 第二局-诡术之境",
          "链接": "https://www.bilibili.com/video/BV1DijD6BE4g"
        },
        {
          "标题": "20260623 正赛 第四期 Day-1 第三局-机械狼通灵师",
          "链接": "https://www.bilibili.com/video/BV18ijD6BExE"
        },
        {
          "标题": "20260624 正赛 第四期 Day-2 第一局-预女猎白混",
          "链接": "https://www.bilibili.com/video/BV1QAjo6sEEc"
        },
        {
          "标题": "20260624 正赛 第四期 Day-2 第二局-诡术之境",
          "链接": "https://www.bilibili.com/video/BV1QAjo6sEaN"
        },
        {
          "标题": "20260624 正赛 第四期 Day-2 第三局-机械狼通灵师",
          "链接": "https://www.bilibili.com/video/BV13Ajo6xEY8"
        }
      ]
    }
  ],
  "粤小": [
    {
      "来源": "https://space.bilibili.com/19106800/lists/7029089?type=season",
      "mid": 19106800,
      "合集ID": 7029089,
      "合集标题": "大湾区小师赛",
      "视频": [
        {
          "标题": "20251220 大湾区小师赛首播第一天",
          "链接": "https://www.bilibili.com/video/BV1DsBXB8Edh"
        },
        {
          "标题": "20251221 大湾区小师赛首播第二天",
          "链接": "https://www.bilibili.com/video/BV1u2BQB4EdE"
        },
        {
          "标题": "20251222 大湾区小师赛首播第三天",
          "链接": "https://www.bilibili.com/video/BV13kBQBFEYm"
        },
        {
          "标题": "20251227   大湾区小师赛",
          "链接": "https://www.bilibili.com/video/BV1UeviBBE6j"
        },
        {
          "标题": "20251228   大湾区小师赛",
          "链接": "https://www.bilibili.com/video/BV1gNvyBhEmY"
        },
        {
          "标题": "20260103  大湾区小师赛",
          "链接": "https://www.bilibili.com/video/BV17qinBLECK"
        },
        {
          "标题": "20260104 大湾区小师赛",
          "链接": "https://www.bilibili.com/video/BV1g3inBAE4z"
        },
        {
          "标题": "20260105 大湾区小师赛 第一局-预女猎白混",
          "链接": "https://www.bilibili.com/video/BV123itBLEZr"
        },
        {
          "标题": "20260105 大湾区小师赛 第二局-狼美人猎人",
          "链接": "https://www.bilibili.com/video/BV1BtitBeECE"
        },
        {
          "标题": "20260105 大湾区小师赛 第三局-机械狼通灵师",
          "链接": "https://www.bilibili.com/video/BV1BniZBDEoa"
        },
        {
          "标题": "20260124 第一局 预女猎白混",
          "链接": "https://www.bilibili.com/video/BV12NzyBNEX9"
        },
        {
          "标题": "202601 26第一局+第二局",
          "链接": "https://www.bilibili.com/video/BV1vVziBoEVb"
        },
        {
          "标题": "20260124DAY7 第四局",
          "链接": "https://www.bilibili.com/video/BV1vVziBoEiN"
        },
        {
          "标题": "20260126 第三局",
          "链接": "https://www.bilibili.com/video/BV1vVziBoEyf"
        },
        {
          "标题": "2026-02-01第一局预女猎白混",
          "链接": "https://www.bilibili.com/video/BV1hF68BKELP"
        },
        {
          "标题": "2026-02-01第二局假面舞会",
          "链接": "https://www.bilibili.com/video/BV1AY6bBREXm"
        },
        {
          "标题": "2026-02-02第一局预女猎白混",
          "链接": "https://www.bilibili.com/video/BV1MHFTzHEvm"
        },
        {
          "标题": "2026-02-02第二局盗宝大师",
          "链接": "https://www.bilibili.com/video/BV1WDFKzkEnQ"
        },
        {
          "标题": "2026-02-02第三局机械狼通灵师",
          "链接": "https://www.bilibili.com/video/BV17mFuzGE2j"
        },
        {
          "标题": "2026-02-10第一局预女猎白混",
          "链接": "https://www.bilibili.com/video/BV1x3F9zyEmz"
        },
        {
          "标题": "2026-02-10第二局假面舞会",
          "链接": "https://www.bilibili.com/video/BV1x3F9zyEQR"
        },
        {
          "标题": "2026-02-10第三局机械狼通灵师",
          "链接": "https://www.bilibili.com/video/BV1x3F9zyE3w"
        },
        {
          "标题": "2026-02-10第四局混血儿加班",
          "链接": "https://www.bilibili.com/video/BV18wF9zDEgC"
        },
        {
          "标题": "2026-02-11-19第一局预女猎白混",
          "链接": "https://www.bilibili.com/video/BV1LectzoESM"
        },
        {
          "标题": "2026-02-11第二局假面舞会",
          "链接": "https://www.bilibili.com/video/BV1vectzoEp9"
        },
        {
          "标题": "2026-02-11第三局抄牌+第四局机械狼通灵师",
          "链接": "https://www.bilibili.com/video/BV1LectzoE9x"
        },
        {
          "标题": "2026-02-12大湾区小师赛第一局预女猎白混",
          "链接": "https://www.bilibili.com/video/BV1yTcGzFEri"
        },
        {
          "标题": "2026-02-12大湾区小师赛第二局+第三局假面舞会机械狼",
          "链接": "https://www.bilibili.com/video/BV11TcGzFE4a"
        },
        {
          "标题": "2026-02-12大湾区小师赛第四局机械狼",
          "链接": "https://www.bilibili.com/video/BV1yTcGzFErt"
        },
        {
          "标题": "2026-02-13大湾区小师赛第二局盗宝大师",
          "链接": "https://www.bilibili.com/video/BV1AmcHz9Exv"
        },
        {
          "标题": "2026-02-13大湾区小师赛",
          "链接": "https://www.bilibili.com/video/BV1AmcHz9Ex6"
        },
        {
          "标题": "2026-02-14大湾区双头赛第一局预女猎白混",
          "链接": "https://www.bilibili.com/video/BV1ZxZEB8Eod"
        },
        {
          "标题": "2026-02-14大湾区双头赛第二局盗宝",
          "链接": "https://www.bilibili.com/video/BV1fxZEB8E2j"
        },
        {
          "标题": "2026-02-14大湾区双头赛第三局机械狼",
          "链接": "https://www.bilibili.com/video/BV1fxZEB8E2P"
        },
        {
          "标题": "2026-02-28大湾区小师赛第一局预女猎白混",
          "链接": "https://www.bilibili.com/video/BV1uvAezME5w"
        },
        {
          "标题": "2026-02-28大湾区小师赛第二局盗宝大师",
          "链接": "https://www.bilibili.com/video/BV1uvAezME5T"
        },
        {
          "标题": "2026-02-28大湾区小师赛第三局机械狼",
          "链接": "https://www.bilibili.com/video/BV1uvAezME1U"
        },
        {
          "标题": "2026-03-01-19大湾区小师赛第一局预女猎白混",
          "链接": "https://www.bilibili.com/video/BV1S7PuziEY4"
        },
        {
          "标题": "2026-03-01-20大湾区小师赛第二局假面舞会",
          "链接": "https://www.bilibili.com/video/BV1S7PuziEbK"
        },
        {
          "标题": "2026-03-01大湾区小师赛第三局机械狼",
          "链接": "https://www.bilibili.com/video/BV1S7PuziEBD"
        },
        {
          "标题": "2026-01-24大湾区小师赛第二局",
          "链接": "https://www.bilibili.com/video/BV1GgPuzGE1y"
        },
        {
          "标题": "2026-01-24大湾区小师赛第三局",
          "链接": "https://www.bilibili.com/video/BV1XgPuz3EhK"
        },
        {
          "标题": "2026-01-25大湾区小师赛第三局",
          "链接": "https://www.bilibili.com/video/BV1kYPuzxEWK"
        },
        {
          "标题": "2026-03-02大湾区小师赛第一局预女猎白混",
          "链接": "https://www.bilibili.com/video/BV1MiP7z4EH1"
        },
        {
          "标题": "2026-03-02大湾区小师赛第二局盗宝大师",
          "链接": "https://www.bilibili.com/video/BV1MiP7z4ESA"
        },
        {
          "标题": "2026-03-02大湾区小师赛第三局机械狼",
          "链接": "https://www.bilibili.com/video/BV1MiP7z4EGk"
        },
        {
          "标题": "2026-03-07大湾区小师赛第一局预女猎白混",
          "链接": "https://www.bilibili.com/video/BV1bENPzsEjx"
        },
        {
          "标题": "2026-03-07大湾区小师赛第二局傀儡",
          "链接": "https://www.bilibili.com/video/BV1uENPzsEKV"
        },
        {
          "标题": "2026-03-07大湾区小师赛第三局机械狼",
          "链接": "https://www.bilibili.com/video/BV1UENPzsEac"
        },
        {
          "标题": "2026-03-08大湾区小师赛第一局预女猎白混",
          "链接": "https://www.bilibili.com/video/BV117N3zMEcC"
        },
        {
          "标题": "2026-03-08大湾区小师赛第二局傀儡",
          "链接": "https://www.bilibili.com/video/BV117N3zMEeh"
        },
        {
          "标题": "2026-03-08-22第三局机械狼",
          "链接": "https://www.bilibili.com/video/BV127N3zMEcR"
        },
        {
          "标题": "2026-03-09大湾区小师赛第一局预女猎白混",
          "链接": "https://www.bilibili.com/video/BV1ptPXzUEdq"
        },
        {
          "标题": "2026-03-09大湾区小师赛第二局傀儡",
          "链接": "https://www.bilibili.com/video/BV1WtPXzUEqx"
        },
        {
          "标题": "2026-03-09大湾区小师赛第三局机械狼",
          "链接": "https://www.bilibili.com/video/BV1WtPXzSEGW"
        },
        {
          "标题": "2026-03-14大湾区小师赛第一局预女猎白混",
          "链接": "https://www.bilibili.com/video/BV189wbzdEZv"
        },
        {
          "标题": "2026-03-14大湾区小师赛第二局盗宝大师",
          "链接": "https://www.bilibili.com/video/BV1Q9wbzdExk"
        },
        {
          "标题": "2026-03-14大湾区小师赛第三局机械狼",
          "链接": "https://www.bilibili.com/video/BV1h9wbzdE85"
        },
        {
          "标题": "2026-03-15大湾区小师赛第一局预女猎白混",
          "链接": "https://www.bilibili.com/video/BV1WewgzoE4g"
        },
        {
          "标题": "2026-03-15大湾区小师赛第二局盗宝大师",
          "链接": "https://www.bilibili.com/video/BV1pewgzoERn"
        },
        {
          "标题": "2026-03-15大湾区小师赛第三局机械狼",
          "链接": "https://www.bilibili.com/video/BV1WewgzoEST"
        },
        {
          "标题": "2026-03-16第一局预女猎白混",
          "链接": "https://www.bilibili.com/video/BV1UUw1zPEHi"
        },
        {
          "标题": "2026-03-16大湾区小师赛第二局盗宝大师",
          "链接": "https://www.bilibili.com/video/BV1MUw1zNErm"
        },
        {
          "标题": "2026-03-14第三+四局机械狼狼美人",
          "链接": "https://www.bilibili.com/video/BV1SUw1zPEGA"
        },
        {
          "标题": "2026-03-21大湾区小师赛第一局预女猎白混",
          "链接": "https://www.bilibili.com/video/BV1rkATzmEwu"
        },
        {
          "标题": "2026-03-21第二局假面舞会",
          "链接": "https://www.bilibili.com/video/BV16kATzmEoY"
        },
        {
          "标题": "2026-03-21第三局机械狼",
          "链接": "https://www.bilibili.com/video/BV1rkATzmEKt"
        },
        {
          "标题": "2026-03-22大湾区小师赛第一局预女猎白混",
          "链接": "https://www.bilibili.com/video/BV1oHQXBzEKU"
        },
        {
          "标题": "2026-03-22大湾区小师赛第二局盗宝大师",
          "链接": "https://www.bilibili.com/video/BV1iHQXBzEbF"
        },
        {
          "标题": "2026-03-23大湾区小师赛第二局诡术之境",
          "链接": "https://www.bilibili.com/video/BV1mMQfBkEQW"
        },
        {
          "标题": "2026-03-23大湾区小师赛第三局机械狼",
          "链接": "https://www.bilibili.com/video/BV1UMQfBkEYP"
        },
        {
          "标题": "2026-03-28大湾区小师赛第一局预女猎白混",
          "链接": "https://www.bilibili.com/video/BV19HX1BJEBW"
        },
        {
          "标题": "2026-03-28大湾区小师赛第二局假面舞会",
          "链接": "https://www.bilibili.com/video/BV19HX1BJEoM"
        },
        {
          "标题": "2026-03-28大湾区小师赛第三局机械狼",
          "链接": "https://www.bilibili.com/video/BV1RHX1BJEN2"
        },
        {
          "标题": "2026-03-28大湾区小师赛第四局狼美骑",
          "链接": "https://www.bilibili.com/video/BV19HX1BJEdR"
        },
        {
          "标题": "2026-03-29大湾区小师赛第一局预女猎白混",
          "链接": "https://www.bilibili.com/video/BV1PjX9BdEGb"
        },
        {
          "标题": "2026-03-29大湾区小师赛第二局诡术之境",
          "链接": "https://www.bilibili.com/video/BV1AjX9BdEfA"
        },
        {
          "标题": "2026-03-29大湾区小师赛第三局机械狼",
          "链接": "https://www.bilibili.com/video/BV1PjX9BdE7J"
        },
        {
          "标题": "2026-03-30大湾区小师赛第一局预女猎白混",
          "链接": "https://www.bilibili.com/video/BV15EXeBXEDP"
        },
        {
          "标题": "2026-03-30大湾区小师赛第二局诡术之境",
          "链接": "https://www.bilibili.com/video/BV1LEXeBXEMa"
        },
        {
          "标题": "2026-03-30大湾区小师赛第三局机械狼",
          "链接": "https://www.bilibili.com/video/BV1LEXeBXEHy"
        },
        {
          "标题": "2026-04-04大湾区小师赛第一局预女猎白混",
          "链接": "https://www.bilibili.com/video/BV1RbD5B4E8b"
        },
        {
          "标题": "2026-04-04大湾区小师赛第二局狼美骑流局",
          "链接": "https://www.bilibili.com/video/BV1BHD5BwE54"
        },
        {
          "标题": "2026-04-04大湾区小师赛第三局机械狼",
          "链接": "https://www.bilibili.com/video/BV1BHD5BwEgT"
        },
        {
          "标题": "2026-04-04大湾区小师赛第四局狼美骑",
          "链接": "https://www.bilibili.com/video/BV1qHD5BwEki"
        },
        {
          "标题": "2026-04-05大湾区小师赛第一局预女猎白混+第二局流局",
          "链接": "https://www.bilibili.com/video/BV169SSBPECa"
        },
        {
          "标题": "2026-04-05大湾区小师赛第三局机械狼通灵师",
          "链接": "https://www.bilibili.com/video/BV1F9SSBPEap"
        },
        {
          "标题": "2026-04-06大湾区小师赛第一局预女猎白混",
          "链接": "https://www.bilibili.com/video/BV1rpD8B2EtP"
        },
        {
          "标题": "2026-04-06大湾区小师赛第二局诡术之境",
          "链接": "https://www.bilibili.com/video/BV1HpD8B2Exk"
        },
        {
          "标题": "2026-04-06大湾区小师赛第三局机械狼",
          "链接": "https://www.bilibili.com/video/BV1HpD8B2EMF"
        },
        {
          "标题": "2026-04-11大湾区小师赛第一局预女猎白混",
          "链接": "https://www.bilibili.com/video/BV1KfDCB8EkV"
        },
        {
          "标题": "2026-04-11大湾区小师赛第二局盗宝大师",
          "链接": "https://www.bilibili.com/video/BV1KfDCB8EQF"
        },
        {
          "标题": "2026-04-11大湾区小师赛第三局机械狼",
          "链接": "https://www.bilibili.com/video/BV14fDCB8EGc"
        },
        {
          "标题": "2026-04-11大湾区小师赛第四局狼美人骑士",
          "链接": "https://www.bilibili.com/video/BV12fDCBbENV"
        },
        {
          "标题": "2026-04-12大湾区小师赛第一局预女猎白混",
          "链接": "https://www.bilibili.com/video/BV1ngDdBDEqV"
        },
        {
          "标题": "2026-04-12大湾区小师赛第二局+第三局",
          "链接": "https://www.bilibili.com/video/BV16gDdBDEkR"
        },
        {
          "标题": "2026-04-13大湾区小师赛第一局预女猎白混",
          "链接": "https://www.bilibili.com/video/BV1F9Q8BJE4W"
        },
        {
          "标题": "2026-04-13大湾区小师赛第二局诡术之境",
          "链接": "https://www.bilibili.com/video/BV1n9Q8BJEDH"
        },
        {
          "标题": "2026-04-13大湾区小师赛第三局机械狼",
          "链接": "https://www.bilibili.com/video/BV1c9Q8BJEGp"
        },
        {
          "标题": "2026-04-18大湾区小师赛第一局预女猎白混",
          "链接": "https://www.bilibili.com/video/BV15XdxBuE6w"
        },
        {
          "标题": "2026-04-18大湾区小师赛第二局假面舞会",
          "链接": "https://www.bilibili.com/video/BV1eXdxBMEdb"
        },
        {
          "标题": "2026-04-18大湾区小师赛第三局机械狼",
          "链接": "https://www.bilibili.com/video/BV1eXdxBMEJN"
        },
        {
          "标题": "2026-04-19大湾区小师赛第一局预女猎白混",
          "链接": "https://www.bilibili.com/video/BV1dGowB3EHE"
        },
        {
          "标题": "2026-04-19大湾区小师赛第二局假面舞会",
          "链接": "https://www.bilibili.com/video/BV1qGowBGEHr"
        },
        {
          "标题": "2026-04-19-21大湾区小师赛第三局机械狼",
          "链接": "https://www.bilibili.com/video/BV1dGowB3Emi"
        },
        {
          "标题": "2026-04-20大湾区小师赛第一局预女猎白混",
          "链接": "https://www.bilibili.com/video/BV13mdkB2EbF"
        },
        {
          "标题": "2026-04-20大湾区小师赛第二局诡术之境",
          "链接": "https://www.bilibili.com/video/BV1DmdkB1E4f"
        },
        {
          "标题": "2026-04-20大湾区小师赛第三局机械狼",
          "链接": "https://www.bilibili.com/video/BV13mdkB2Et9"
        },
        {
          "标题": "2026-04-20-22大湾区小师赛第四局狼美骑",
          "链接": "https://www.bilibili.com/video/BV1hmdkB2Es9"
        },
        {
          "标题": "2026-04-25大湾区小师赛第一局预女猎白混",
          "链接": "https://www.bilibili.com/video/BV1HvoXBbEuo"
        },
        {
          "标题": "2026-04-25大湾区小师赛第二局诡术之境",
          "链接": "https://www.bilibili.com/video/BV1cvoXB8E7N"
        },
        {
          "标题": "2026-04-25大湾区小师赛第三局机械狼",
          "链接": "https://www.bilibili.com/video/BV16voXBbEUK"
        },
        {
          "标题": "2026-04-26大湾区小师赛第一局预女猎白混",
          "链接": "https://www.bilibili.com/video/BV1a1oqBiEpn"
        },
        {
          "标题": "2026-04-26-21-00-30",
          "链接": "https://www.bilibili.com/video/BV1G1oqBiEg1"
        },
        {
          "标题": "2026-04-26大湾区小师赛第三局机械狼",
          "链接": "https://www.bilibili.com/video/BV1G1oqBiELL"
        },
        {
          "标题": "2026-04-27大湾区小师赛第一局预女猎白混",
          "链接": "https://www.bilibili.com/video/BV1GT9rBMEMG"
        },
        {
          "标题": "2026-04-27大湾区小师赛第二局盗宝大师",
          "链接": "https://www.bilibili.com/video/BV1QT9rBTE2F"
        },
        {
          "标题": "2026-04-27大湾区小师赛第三局机械狼通灵师",
          "链接": "https://www.bilibili.com/video/BV1QT9rBTE1U"
        },
        {
          "标题": "2026-05-02大湾区小师赛第一局预女猎白混",
          "链接": "https://www.bilibili.com/video/BV1CC9QBpEs7"
        },
        {
          "标题": "2026-05-02大湾区小师赛第二局盗宝大师",
          "链接": "https://www.bilibili.com/video/BV1CC9QBpECc"
        },
        {
          "标题": "2026-05-02大湾区小师赛第三局",
          "链接": "https://www.bilibili.com/video/BV1CC9QBpEQz"
        },
        {
          "标题": "2026-05-03大湾区小师赛第一局预女猎白混",
          "链接": "https://www.bilibili.com/video/BV14iRABoE47"
        },
        {
          "标题": "2026-05-03大湾区小师赛第二局诡术之境",
          "链接": "https://www.bilibili.com/video/BV14iRABoE1D"
        },
        {
          "标题": "2026-05-03大湾区小师赛第三局机械狼通灵师",
          "链接": "https://www.bilibili.com/video/BV1miRABoEJj"
        },
        {
          "标题": "2026-05-04大湾区小师赛第一局预女猎白混",
          "链接": "https://www.bilibili.com/video/BV1QQRBBYEK3"
        },
        {
          "标题": "2026-05-04大湾区小师赛第二局盗宝大师",
          "链接": "https://www.bilibili.com/video/BV13QRBBeEoZ"
        },
        {
          "标题": "2026-05-04大湾区小师赛第三局机械狼",
          "链接": "https://www.bilibili.com/video/BV1QQRBBYEKA"
        },
        {
          "标题": "2026-05-09大湾区小师赛第一局预女猎白混",
          "链接": "https://www.bilibili.com/video/BV15kRfBcE12"
        },
        {
          "标题": "2026-05-09大湾区小师赛第二局唯令是从",
          "链接": "https://www.bilibili.com/video/BV1L6RfBaE1E"
        },
        {
          "标题": "2026-05-09大湾区小师赛第三局机械狼通灵师",
          "链接": "https://www.bilibili.com/video/BV1L6RfBaERt"
        },
        {
          "标题": "2026-05-10大湾区小师赛第一局预女猎白混",
          "链接": "https://www.bilibili.com/video/BV1pH5H6BE5m"
        },
        {
          "标题": "2026-05-10大湾区小师赛第二局狼美人骑士",
          "链接": "https://www.bilibili.com/video/BV1HH5H6BERp"
        },
        {
          "标题": "2026-05-10大湾区小师赛第三局假面舞会",
          "链接": "https://www.bilibili.com/video/BV1pH5H6BErN"
        },
        {
          "标题": "2026-05-11大湾区小师赛第一局假面舞会",
          "链接": "https://www.bilibili.com/video/BV1cv5N6REwS"
        },
        {
          "标题": "2026-05-11大湾区小师赛第二局孤注一掷",
          "链接": "https://www.bilibili.com/video/BV1cv5N6REeS"
        },
        {
          "标题": "2026-05-11大湾区小师赛第三局盗宝大师",
          "链接": "https://www.bilibili.com/video/BV1cv5N6RE8V"
        },
        {
          "标题": "2026-05-12大湾区小师赛第四局诡术之境",
          "链接": "https://www.bilibili.com/video/BV1cv5N6REek"
        },
        {
          "标题": "2026-05-16大湾区小师赛第二局魔鬼骑",
          "链接": "https://www.bilibili.com/video/BV1PaLV6XEKp"
        },
        {
          "标题": "2026-05-16大湾区小师赛第二局机械狼",
          "链接": "https://www.bilibili.com/video/BV1PaLV6XEKn"
        },
        {
          "标题": "2026-05-17大湾区小师赛第一局预女猎白混",
          "链接": "https://www.bilibili.com/video/BV1ADLH6kEJe"
        },
        {
          "标题": "2026-05-17大湾区小师赛第二局盗宝大师",
          "链接": "https://www.bilibili.com/video/BV1ADLH6kEJB"
        },
        {
          "标题": "2026-05-17大湾区小师赛第三局机械狼",
          "链接": "https://www.bilibili.com/video/BV1wDLH6kECT"
        },
        {
          "标题": "2026-05-18大湾区小师赛第一局+第二局",
          "链接": "https://www.bilibili.com/video/BV1JmLK6bEdV"
        },
        {
          "标题": "2026-05-18大湾区小师赛第三局机械狼",
          "链接": "https://www.bilibili.com/video/BV1H2LK6FEFT"
        },
        {
          "标题": "2026-05-23大湾区小师赛杭粤总决赛完整版",
          "链接": "https://www.bilibili.com/video/BV16yG66mEeU"
        },
        {
          "标题": "2026-05-24杭粤总决赛第一局机械狼",
          "链接": "https://www.bilibili.com/video/BV1ycGH6NEkn"
        },
        {
          "标题": "2026-05-24杭粤总决赛第二局诡术之境",
          "链接": "https://www.bilibili.com/video/BV1NcGH6KEwa"
        },
        {
          "标题": "2026-05-24杭粤总决赛第三局盗宝大师",
          "链接": "https://www.bilibili.com/video/BV1ycGH6NEg8"
        },
        {
          "标题": "2026-05-25杭粤总决赛第一局机械狼",
          "链接": "https://www.bilibili.com/video/BV1RUGf6oEn8"
        },
        {
          "标题": "2026-05-25大湾区杭粤总决赛第二局石像鬼",
          "链接": "https://www.bilibili.com/video/BV1RUGf6oEgr"
        },
        {
          "标题": "2026-05-25大湾区杭粤总决赛第三局+颁奖仪式",
          "链接": "https://www.bilibili.com/video/BV19UGf6oEof"
        },
        {
          "标题": "2026-05-30大湾区小师赛第一局预女猎白混",
          "链接": "https://www.bilibili.com/video/BV1JtVL6jE1w"
        },
        {
          "标题": "2026-05-30大湾区小师赛第二局诡术之境",
          "链接": "https://www.bilibili.com/video/BV16tVL6jEuH"
        },
        {
          "标题": "2026-05-30大湾区小师赛第三局机械狼",
          "链接": "https://www.bilibili.com/video/BV1JtVL6jEym"
        },
        {
          "标题": "2026-05-31大湾区小师赛第一局预女猎白混",
          "链接": "https://www.bilibili.com/video/BV1kmVD6JE7s"
        },
        {
          "标题": "2026-05-31大湾区小师赛第二局假面舞会",
          "链接": "https://www.bilibili.com/video/BV1wmVD6nExm"
        },
        {
          "标题": "2026-05-31大湾区小师赛第三局机械狼",
          "链接": "https://www.bilibili.com/video/BV1rmVD6JEoV"
        },
        {
          "标题": "2026-05-31大湾区小师赛第四局狼美骑",
          "链接": "https://www.bilibili.com/video/BV1wmVD6nEoz"
        },
        {
          "标题": "2026-06-01大湾区小师赛第一局预女猎白混",
          "链接": "https://www.bilibili.com/video/BV1AJVf6rEDe"
        },
        {
          "标题": "2026-06-01大湾区小师赛第二局假面舞会",
          "链接": "https://www.bilibili.com/video/BV1AJVf6rEAk"
        },
        {
          "标题": "2026-06-06大湾区小师赛6+6第一局",
          "链接": "https://www.bilibili.com/video/BV17TEp6kEa5"
        },
        {
          "标题": "2026-06-06大湾区小师赛6+6第二局",
          "链接": "https://www.bilibili.com/video/BV1qTEp6rEw1"
        },
        {
          "标题": "2026-06-06-21大湾区小师赛6+6第三局第四局",
          "链接": "https://www.bilibili.com/video/BV1eGEp6MEoq"
        },
        {
          "标题": "2026-06-07大湾区小师赛第一局预女猎白混",
          "链接": "https://www.bilibili.com/video/BV1opEh6YEeX"
        },
        {
          "标题": "2026-06-07大湾区小师赛第二局假面舞会",
          "链接": "https://www.bilibili.com/video/BV1opEh6YEvn"
        },
        {
          "标题": "2026-06-07大湾区小师赛第三局机械狼",
          "链接": "https://www.bilibili.com/video/BV1ipEh6YERd"
        },
        {
          "标题": "2026-06-08大湾区小师赛第一局预女猎白混",
          "链接": "https://www.bilibili.com/video/BV1wkEV6oETg"
        },
        {
          "标题": "2026-06-08大湾区小师赛第二局盗宝大师",
          "链接": "https://www.bilibili.com/video/BV1krEV64Ekg"
        },
        {
          "标题": "2026-06-08大湾区小师赛第三局机械狼",
          "链接": "https://www.bilibili.com/video/BV1krEV64EB8"
        },
        {
          "标题": "2026-06-13大湾区小师赛第一局预女猎白混",
          "链接": "https://www.bilibili.com/video/BV1dWJx6nERw"
        },
        {
          "标题": "2026-06-13大湾区小师赛第二局假面舞会",
          "链接": "https://www.bilibili.com/video/BV1dWJx6nEpe"
        },
        {
          "标题": "2026-06-13大湾区小师赛第二局机械狼",
          "链接": "https://www.bilibili.com/video/BV1oHJx6QE6Q"
        },
        {
          "标题": "2026-06-14 大湾区小师赛第一局+第二局",
          "链接": "https://www.bilibili.com/video/BV1hJJK6pEBs"
        },
        {
          "标题": "2026-06-14 大湾区小师赛第三局机械狼",
          "链接": "https://www.bilibili.com/video/BV137JK69EmQ"
        },
        {
          "标题": "2026-06-15大湾区小师赛第一局预女猎白混",
          "链接": "https://www.bilibili.com/video/BV1tLjP6iENF"
        },
        {
          "标题": "2026-06-15大湾区小师赛第二局诡术之境",
          "链接": "https://www.bilibili.com/video/BV1tLjP6iEE1"
        },
        {
          "标题": "2026-06-15大湾区小师赛第三局机械狼",
          "链接": "https://www.bilibili.com/video/BV1bLjP6iEw9"
        },
        {
          "标题": "2026-06-15大湾区小师赛第四局狼美人",
          "链接": "https://www.bilibili.com/video/BV1b5jP6TE7n"
        },
        {
          "标题": "2026-06-20大湾区小师赛第一局+第二局",
          "链接": "https://www.bilibili.com/video/BV1QCjp6FEB6"
        },
        {
          "标题": "2026-06-20大湾区小师赛第三局机械狼",
          "链接": "https://www.bilibili.com/video/BV1hCjp6FEf7"
        },
        {
          "标题": "2026-06-21大湾区小师赛第一局预女猎白混",
          "链接": "https://www.bilibili.com/video/BV1Gz7K6QEmq"
        },
        {
          "标题": "2026-06-21大湾区小师赛第二局诡术之境",
          "链接": "https://www.bilibili.com/video/BV1Gz7K6QE5Q"
        },
        {
          "标题": "2026-06-21-21大湾区小师赛第三局机械狼",
          "链接": "https://www.bilibili.com/video/BV1Gz7K6QExL"
        },
        {
          "标题": "2026-06-21大湾区小师赛第四局机械狼",
          "链接": "https://www.bilibili.com/video/BV1La7K64EfK"
        },
        {
          "标题": "2026-06-22大湾区小师赛第一局预女猎白混",
          "链接": "https://www.bilibili.com/video/BV1Kv7T65Eeo"
        },
        {
          "标题": "2026-06-22大湾区小师赛第二局诡术之境",
          "链接": "https://www.bilibili.com/video/BV1qQ7T6aEti"
        }
      ]
    }
  ]
}